pyqt_phone_input/__init__.py
pyqt_phone_input/countries.py
pyqt_phone_input/country_dropdown.py
pyqt_phone_input/phone_input.py
pyqt_phone_input/phone_line_edit.py
pyqt_phone_input/flag_icons/ad.png
pyqt_phone_input/flag_icons/ae.png
pyqt_phone_input/flag_icons/af.png
pyqt_phone_input/flag_icons/ag.png
pyqt_phone_input/flag_icons/ai.png
pyqt_phone_input/flag_icons/al.png
pyqt_phone_input/flag_icons/am.png
pyqt_phone_input/flag_icons/ao.png
pyqt_phone_input/flag_icons/ar.png
pyqt_phone_input/flag_icons/as.png
pyqt_phone_input/flag_icons/at.png
pyqt_phone_input/flag_icons/au.png
pyqt_phone_input/flag_icons/aw.png
pyqt_phone_input/flag_icons/az.png
pyqt_phone_input/flag_icons/ba.png
pyqt_phone_input/flag_icons/bb.png
pyqt_phone_input/flag_icons/bd.png
pyqt_phone_input/flag_icons/be.png
pyqt_phone_input/flag_icons/bf.png
pyqt_phone_input/flag_icons/bg.png
pyqt_phone_input/flag_icons/bh.png
pyqt_phone_input/flag_icons/bi.png
pyqt_phone_input/flag_icons/bj.png
pyqt_phone_input/flag_icons/bl.png
pyqt_phone_input/flag_icons/bm.png
pyqt_phone_input/flag_icons/bn.png
pyqt_phone_input/flag_icons/bo.png
pyqt_phone_input/flag_icons/bq.png
pyqt_phone_input/flag_icons/br.png
pyqt_phone_input/flag_icons/bs.png
pyqt_phone_input/flag_icons/bt.png
pyqt_phone_input/flag_icons/bw.png
pyqt_phone_input/flag_icons/by.png
pyqt_phone_input/flag_icons/bz.png
pyqt_phone_input/flag_icons/ca.png
pyqt_phone_input/flag_icons/cd.png
pyqt_phone_input/flag_icons/cf.png
pyqt_phone_input/flag_icons/cg.png
pyqt_phone_input/flag_icons/ch.png
pyqt_phone_input/flag_icons/ci.png
pyqt_phone_input/flag_icons/ck.png
pyqt_phone_input/flag_icons/cl.png
pyqt_phone_input/flag_icons/cm.png
pyqt_phone_input/flag_icons/cn.png
pyqt_phone_input/flag_icons/co.png
pyqt_phone_input/flag_icons/cr.png
pyqt_phone_input/flag_icons/cu.png
pyqt_phone_input/flag_icons/cv.png
pyqt_phone_input/flag_icons/cw.png
pyqt_phone_input/flag_icons/cy.png
pyqt_phone_input/flag_icons/cz.png
pyqt_phone_input/flag_icons/de.png
pyqt_phone_input-1.0.2.dist-info/LICENSE
pyqt_phone_input-1.0.2.dist-info/METADATA
pyqt_phone_input-1.0.2.dist-info/WHEEL
pyqt_phone_input-1.0.2.dist-info/entry_points.txt
pyqt_phone_input-1.0.2.dist-info/top_level.txt
pyqt_phone_input-1.0.2.dist-info/RECORD
