Metadata-Version: 2.1
Name: pyqt-phone-input
Version: 1.0.2
Summary: A clean and modern phone number input widget for PyQt and PySide
Home-page: https://github.com/marcohenning/pyqt-phone-input
Author: Marco Henning
License: MIT
Keywords: python,pyqt,qt,phone
Classifier: Programming Language :: Python :: 3
Classifier: Operating System :: OS Independent
Classifier: License :: OSI Approved :: MIT License
Requires-Python: >=3.7
License-File: LICENSE
Requires-Dist: QtPy>=2.4.1
